aiosfpubsub/__init__.py
aiosfpubsub/client.py
aiosfpubsub/pubsub_api_pb2.py
aiosfpubsub/pubsub_api_pb2_grpc.py
aiosfpubsub-0.0.6.dist-info/LICENSE
aiosfpubsub-0.0.6.dist-info/METADATA
aiosfpubsub-0.0.6.dist-info/WHEEL
aiosfpubsub-0.0.6.dist-info/top_level.txt
aiosfpubsub-0.0.6.dist-info/RECORD
