Metadata-Version: 2.1
Name: aiosfpubsub
Version: 0.0.6
Summary: An async Python gRPC client for the Salesforce PubSub API.
Author-email: Benton Snyder <benton@bensnyde.me>
Project-URL: Homepage, https://github.com/bensnyde/aiosfpubsub
Project-URL: Issues, https://github.com/bensnyde/aiosfpubsub/issues
Keywords: sf,salesforce,pubsub,pub/sub
Classifier: Programming Language :: Python :: 3
Classifier: Operating System :: OS Independent
Requires-Python: >=3.8
License-File: LICENSE
